vantage6/types/__init__.py
vantage6_types-0.1.0.dist-info/licenses/LICENSE
vantage6_types-0.1.0.dist-info/METADATA
vantage6_types-0.1.0.dist-info/WHEEL
vantage6_types-0.1.0.dist-info/top_level.txt
vantage6_types-0.1.0.dist-info/RECORD
