Metadata-Version: 2.4
Name: vantage6_types
Version: 0.1.0
Summary: Type system for vantage6 tabular data
Author-email: Frank Martin <mail@franky.codes>
License: Apache-2.0
Classifier: Programming Language :: Python :: 3
Classifier: Programming Language :: Python :: 3.7
Classifier: Programming Language :: Python :: 3.8
Classifier: Programming Language :: Python :: 3.9
Classifier: Programming Language :: Python :: 3.10
Classifier: License :: OSI Approved :: Apache Software License
Classifier: Operating System :: OS Independent
Requires-Python: >=3.7
License-File: LICENSE
Requires-Dist: pandas>=1.0.0
Requires-Dist: pyarrow>=7.0.0
Requires-Dist: pydantic>=1.8.0
Dynamic: license-file
